textminer/__init__.py
textminer/cleaner.py
textminer/detector.py
textminer/summarizer.py
textminer_pro_jihoonLee-0.1.0.dist-info/METADATA
textminer_pro_jihoonLee-0.1.0.dist-info/WHEEL
textminer_pro_jihoonLee-0.1.0.dist-info/top_level.txt
textminer_pro_jihoonLee-0.1.0.dist-info/RECORD
