Metadata-Version: 2.1
Name: textminer-pro-jihoonLee
Version: 0.1.0
Summary: A simple text mining package with stopword removal, keyword extraction, summarization, and language detection.
Home-page: https://github.com/hoonZeee/Oss_2025/tree/main/pypi
Author: Jihoon Lee
Author-email: dlwlgns7540@naver.com
Classifier: Programming Language :: Python :: 3
Classifier: License :: OSI Approved :: MIT License
Requires-Python: >=3.7
Requires-Dist: nltk
Requires-Dist: scikit-learn
Requires-Dist: sumy
Requires-Dist: langdetect
